TIME.py
pykernel.py
pykernel-0.1.5.dist-info/LICENSE.txt
pykernel-0.1.5.dist-info/METADATA
pykernel-0.1.5.dist-info/WHEEL
pykernel-0.1.5.dist-info/top_level.txt
pykernel-0.1.5.dist-info/RECORD
