Metadata-Version: 2.1
Name: pykernel
Version: 0.1.5
Summary: Python & text Windows CMD Editior written with only native libaries
Home-page: https://github.com/coolnicecool/editor
Author: Raleigh Priour
Author-email: raleigh@1337maps.com
License: LINCENSE.rst
Platform: UNKNOWN
